sdax/__init__.py
sdax/sdax_core.py
sdax/sdax_task_analyser.py
sdax/tasks.py
sdax-0.5.2.dist-info/METADATA
sdax-0.5.2.dist-info/WHEEL
sdax-0.5.2.dist-info/licenses/LICENSE
sdax-0.5.2.dist-info/RECORD
