Metadata-Version: 2.4
Name: sdax
Version: 0.5.2
Summary: A lightweight, high-performance, in-process micro-orchestrator for structured, declarative, and parallel asynchronous tasks in Python.
Project-URL: Homepage, https://github.com/owebeeone/sdax
Project-URL: Issues, https://github.com/owebeeone/sdax/issues
Author-email: Gianni Mariani <gianni@mariani.ws>
License: MIT
License-File: LICENSE
Classifier: Framework :: AsyncIO
Classifier: Intended Audience :: Developers
Classifier: License :: OSI Approved :: MIT License
Classifier: Operating System :: OS Independent
Classifier: Programming Language :: Python :: 3
Classifier: Programming Language :: Python :: 3.11
Classifier: Topic :: Software Development :: Libraries :: Python Modules
Requires-Python: >=3.11
Provides-Extra: dev
Requires-Dist: mypy; extra == 'dev'
Requires-Dist: pytest-asyncio; extra == 'dev'
Requires-Dist: ruff; extra == 'dev'
